Metadata-Version: 2.1
Name: lipandas
Version: 1.0.0
Summary: Load a CSV file into a Pandas DataFrame and open it in IPython.
Home-page: 
Author: João Nogueira
Author-email: joaopcnogueira@gmail.com
License:                                  Apache License
License-File: LICENSE
